variconfig/__init__.py
variconfig/_version.py
variconfig/core/__init__.py
variconfig/core/config.py
variconfig/core/logging_config.py
variconfig/utils/__init__.py
variconfig/utils/config.yml
variconfig/utils/file_utils.py
variconfig/utils/general_utils.py
variconfig-0.0.3.dist-info/LICENSE
variconfig-0.0.3.dist-info/METADATA
variconfig-0.0.3.dist-info/WHEEL
variconfig-0.0.3.dist-info/top_level.txt
variconfig-0.0.3.dist-info/RECORD
