Metadata-Version: 2.1
Name: variconfig
Version: 0.0.3
Summary: VariConfig is a Python package for managing configuration files in a variety of formats and is able to handle variable substitution.
Author-email: Logan Lang <lllang@mix.wvu.edu>
License: MIT License
Project-URL: Repository, https://github.com/romerogroup/VariConfig
Project-URL: Issues, https://github.com/romerogroup/VariConfig/issues
Project-URL: Changelog, https://github.com/romerogroup/VariConfig/CHANGELOG.md
Keywords: config,variable,yaml,json,toml,ini,variables,substitution,config-files
Classifier: Programming Language :: Python :: 3
Requires-Python: >=3.8
License-File: LICENSE
Requires-Dist: python-dotenv
Requires-Dist: toml
Requires-Dist: PyYAML
Provides-Extra: dev
Requires-Dist: sphinx ; extra == 'dev'
Requires-Dist: sphinx-rtd-theme ; extra == 'dev'
